signalflow/__init__.py
signalflow/grammar/SignalFlowV2Lexer.py
signalflow/grammar/SignalFlowV2Parser.py
signalflow/grammar/SignalFlowV2ParserListener.py
signalflow/grammar/SignalFlowV2ParserVisitor.py
signalflow/grammar/__init__.py
signalflow_grammar-2.12.0.dist-info/DESCRIPTION.rst
signalflow_grammar-2.12.0.dist-info/METADATA
signalflow_grammar-2.12.0.dist-info/RECORD
signalflow_grammar-2.12.0.dist-info/WHEEL
signalflow_grammar-2.12.0.dist-info/metadata.json
signalflow_grammar-2.12.0.dist-info/pbr.json
signalflow_grammar-2.12.0.dist-info/top_level.txt
signalflow_grammar-2.12.0.dist-info/zip-safe
