Metadata-Version: 2.0
Name: signalflow-grammar
Version: 2.12.0
Summary: SignalFx SignalFlow language grammar
Home-page: UNKNOWN
Author: UNKNOWN
Author-email: UNKNOWN
License: Apache Software License v2
Platform: UNKNOWN
Requires-Dist: antlr4-python2-runtime
